[{"lohnarbeit":["https://normdb.ivz.cn.ard.de/Arbeiter"],"lohnarbei":["https://normdb.ivz.cn.ard.de/Arbeiter"],"lohnarbe":["https://normdb.ivz.cn.ard.de/Arbeiter"],"lohnarb":["https://normdb.ivz.cn.ard.de/Arbeiter"],"lohnar":["https://normdb.ivz.cn.ard.de/Arbeiter"],"lohna":["https://normdb.ivz.cn.ard.de/Arbeiter"],"lohn":["https://normdb.ivz.cn.ard.de/Arbeiter"],"loh":["https://normdb.ivz.cn.ard.de/Arbeiter"],"lo":["https://normdb.ivz.cn.ard.de/Arbeiter"],"l":["https://normdb.ivz.cn.ard.de/Arbeiter"],"ohnarbeit":["https://normdb.ivz.cn.ard.de/Arbeiter"],"ohnarbei":["https://normdb.ivz.cn.ard.de/Arbeiter"],"ohnarbe":["https://normdb.ivz.cn.ard.de/Arbeiter"],"ohnarb":["https://normdb.ivz.cn.ard.de/Arbeiter"],"ohnar":["https://normdb.ivz.cn.ard.de/Arbeiter"],"ohna":["https://normdb.ivz.cn.ard.de/Arbeiter"],"ohn":["https://normdb.ivz.cn.ard.de/Arbeiter"],"oh":["https://normdb.ivz.cn.ard.de/Arbeiter"],"o":["https://normdb.ivz.cn.ard.de/Arbeiter","https://normdb.ivz.cn.ard.de/Fotograf"],"hnarbeit":["https://normdb.ivz.cn.ard.de/Arbeiter"],"hnarbei":["https://normdb.ivz.cn.ard.de/Arbeiter"],"hnarbe":["https://normdb.ivz.cn.ard.de/Arbeiter"],"hnarb":["https://normdb.ivz.cn.ard.de/Arbeiter"],"hnar":["https://normdb.ivz.cn.ard.de/Arbeiter"],"hna":["https://normdb.ivz.cn.ard.de/Arbeiter"],"hn":["https://normdb.ivz.cn.ard.de/Arbeiter"],"h":["https://normdb.ivz.cn.ard.de/Arbeiter","https://normdb.ivz.cn.ard.de/Fotograf"],"narbeit":["https://normdb.ivz.cn.ard.de/Arbeiter"],"narbei":["https://normdb.ivz.cn.ard.de/Arbeiter"],"narbe":["https://normdb.ivz.cn.ard.de/Arbeiter"],"narb":["https://normdb.ivz.cn.ard.de/Arbeiter"],"nar":["https://normdb.ivz.cn.ard.de/Arbeiter"],"na":["https://normdb.ivz.cn.ard.de/Arbeiter"],"n":["https://normdb.ivz.cn.ard.de/Arbeiter","https://normdb.ivz.cn.ard.de/Bergarbeiter"],"arbeit":["https://normdb.ivz.cn.ard.de/Arbeiter"],"arbei":["https://normdb.ivz.cn.ard.de/Arbeiter"],"arbe":["https://normdb.ivz.cn.ard.de/Arbeiter"],"arb":["https://normdb.ivz.cn.ard.de/Arbeiter"],"ar":["https://normdb.ivz.cn.ard.de/Arbeiter"],"a":["https://normdb.ivz.cn.ard.de/Arbeiter","https://normdb.ivz.cn.ard.de/Bergarbeiter","https://normdb.ivz.cn.ard.de/Fotograf"],"rbeit":["https://normdb.ivz.cn.ard.de/Arbeiter"],"rbei":["https://normdb.ivz.cn.ard.de/Arbeiter"],"rbe":["https://normdb.ivz.cn.ard.de/Arbeiter"],"rb":["https://normdb.ivz.cn.ard.de/Arbeiter"],"r":["https://normdb.ivz.cn.ard.de/Arbeiter","https://normdb.ivz.cn.ard.de/Bergarbeiter","https://normdb.ivz.cn.ard.de/Fotograf"],"beit":["https://normdb.ivz.cn.ard.de/Arbeiter"],"bei":["https://normdb.ivz.cn.ard.de/Arbeiter"],"be":["https://normdb.ivz.cn.ard.de/Arbeiter","https://normdb.ivz.cn.ard.de/Bergarbeiter"],"b":["https://normdb.ivz.cn.ard.de/Arbeiter","https://normdb.ivz.cn.ard.de/Bergarbeiter"],"eit":["https://normdb.ivz.cn.ard.de/Arbeiter"],"ei":["https://normdb.ivz.cn.ard.de/Arbeiter"],"e":["https://normdb.ivz.cn.ard.de/Arbeiter","https://normdb.ivz.cn.ard.de/Bergarbeiter"],"it":["https://normdb.ivz.cn.ard.de/Arbeiter"],"i":["https://normdb.ivz.cn.ard.de/Arbeiter"],"t":["https://normdb.ivz.cn.ard.de/Arbeiter","https://normdb.ivz.cn.ard.de/Fotograf"],"bergmann":["https://normdb.ivz.cn.ard.de/Bergarbeiter"],"bergman":["https://normdb.ivz.cn.ard.de/Bergarbeiter"],"bergma":["https://normdb.ivz.cn.ard.de/Bergarbeiter"],"bergm":["https://normdb.ivz.cn.ard.de/Bergarbeiter"],"berg":["https://normdb.ivz.cn.ard.de/Bergarbeiter"],"ber":["https://normdb.ivz.cn.ard.de/Bergarbeiter"],"ergmann":["https://normdb.ivz.cn.ard.de/Bergarbeiter"],"ergman":["https://normdb.ivz.cn.ard.de/Bergarbeiter"],"ergma":["https://normdb.ivz.cn.ard.de/Bergarbeiter"],"ergm":["https://normdb.ivz.cn.ard.de/Bergarbeiter"],"erg":["https://normdb.ivz.cn.ard.de/Bergarbeiter"],"er":["https://normdb.ivz.cn.ard.de/Bergarbeiter"],"rgmann":["https://normdb.ivz.cn.ard.de/Bergarbeiter"],"rgman":["https://normdb.ivz.cn.ard.de/Bergarbeiter"],"rgma":["https://normdb.ivz.cn.ard.de/Bergarbeiter"],"rgm":["https://normdb.ivz.cn.ard.de/Bergarbeiter"],"rg":["https://normdb.ivz.cn.ard.de/Bergarbeiter"],"gmann":["https://normdb.ivz.cn.ard.de/Bergarbeiter"],"gman":["https://normdb.ivz.cn.ard.de/Bergarbeiter"],"gma":["https://normdb.ivz.cn.ard.de/Bergarbeiter"],"gm":["https://normdb.ivz.cn.ard.de/Bergarbeiter"],"g":["https://normdb.ivz.cn.ard.de/Bergarbeiter","https://normdb.ivz.cn.ard.de/Fotograf"],"mann":["https://normdb.ivz.cn.ard.de/Bergarbeiter"],"man":["https://normdb.ivz.cn.ard.de/Bergarbeiter"],"ma":["https://normdb.ivz.cn.ard.de/Bergarbeiter"],"m":["https://normdb.ivz.cn.ard.de/Bergarbeiter"],"ann":["https://normdb.ivz.cn.ard.de/Bergarbeiter"],"an":["https://normdb.ivz.cn.ard.de/Bergarbeiter"],"nn":["https://normdb.ivz.cn.ard.de/Bergarbeiter"],"fotograph":["https://normdb.ivz.cn.ard.de/Fotograf"],"fotograp":["https://normdb.ivz.cn.ard.de/Fotograf"],"fotogra":["https://normdb.ivz.cn.ard.de/Fotograf"],"fotogr":["https://normdb.ivz.cn.ard.de/Fotograf"],"fotog":["https://normdb.ivz.cn.ard.de/Fotograf"],"foto":["https://normdb.ivz.cn.ard.de/Fotograf"],"fot":["https://normdb.ivz.cn.ard.de/Fotograf"],"fo":["https://normdb.ivz.cn.ard.de/Fotograf"],"f":["https://normdb.ivz.cn.ard.de/Fotograf"],"otograph":["https://normdb.ivz.cn.ard.de/Fotograf"],"otograp":["https://normdb.ivz.cn.ard.de/Fotograf"],"otogra":["https://normdb.ivz.cn.ard.de/Fotograf"],"otogr":["https://normdb.ivz.cn.ard.de/Fotograf"],"otog":["https://normdb.ivz.cn.ard.de/Fotograf"],"oto":["https://normdb.ivz.cn.ard.de/Fotograf"],"ot":["https://normdb.ivz.cn.ard.de/Fotograf"],"tograph":["https://normdb.ivz.cn.ard.de/Fotograf"],"tograp":["https://normdb.ivz.cn.ard.de/Fotograf"],"togra":["https://normdb.ivz.cn.ard.de/Fotograf"],"togr":["https://normdb.ivz.cn.ard.de/Fotograf"],"tog":["https://normdb.ivz.cn.ard.de/Fotograf"],"to":["https://normdb.ivz.cn.ard.de/Fotograf"],"ograph":["https://normdb.ivz.cn.ard.de/Fotograf"],"ograp":["https://normdb.ivz.cn.ard.de/Fotograf"],"ogra":["https://normdb.ivz.cn.ard.de/Fotograf"],"ogr":["https://normdb.ivz.cn.ard.de/Fotograf"],"og":["https://normdb.ivz.cn.ard.de/Fotograf"],"graph":["https://normdb.ivz.cn.ard.de/Fotograf"],"grap":["https://normdb.ivz.cn.ard.de/Fotograf"],"gra":["https://normdb.ivz.cn.ard.de/Fotograf"],"gr":["https://normdb.ivz.cn.ard.de/Fotograf"],"raph":["https://normdb.ivz.cn.ard.de/Fotograf"],"rap":["https://normdb.ivz.cn.ard.de/Fotograf"],"ra":["https://normdb.ivz.cn.ard.de/Fotograf"],"aph":["https://normdb.ivz.cn.ard.de/Fotograf"],"ap":["https://normdb.ivz.cn.ard.de/Fotograf"],"ph":["https://normdb.ivz.cn.ard.de/Fotograf"],"p":["https://normdb.ivz.cn.ard.de/Fotograf"]},{},{},{},{},{},{},{},{}]