[{"0":["https://shoeing1.github.io/MALIS24_NDB/Altphilologe","https://shoeing1.github.io/MALIS24_NDB/Arbeiter","https://shoeing1.github.io/MALIS24_NDB/Architekt","https://shoeing1.github.io/MALIS24_NDB/Archivar","https://shoeing1.github.io/MALIS24_NDB/Astrologe","https://shoeing1.github.io/MALIS24_NDB/Astronom","https://shoeing1.github.io/MALIS24_NDB/Clown","https://shoeing1.github.io/MALIS24_NDB/Gastarbeiter","https://shoeing1.github.io/MALIS24_NDB/Historiker"],"1":["https://shoeing1.github.io/MALIS24_NDB/Altphilologe","https://shoeing1.github.io/MALIS24_NDB/Anatom","https://shoeing1.github.io/MALIS24_NDB/Arbeiter","https://shoeing1.github.io/MALIS24_NDB/Architekt","https://shoeing1.github.io/MALIS24_NDB/Archivar","https://shoeing1.github.io/MALIS24_NDB/Astrologe","https://shoeing1.github.io/MALIS24_NDB/Astronom","https://shoeing1.github.io/MALIS24_NDB/Autor","https://shoeing1.github.io/MALIS24_NDB/Außenminister","https://shoeing1.github.io/MALIS24_NDB/Bakteriologe","https://shoeing1.github.io/MALIS24_NDB/Bergarbeiter","https://shoeing1.github.io/MALIS24_NDB/Bibliothekar","https://shoeing1.github.io/MALIS24_NDB/Botschafter","https://shoeing1.github.io/MALIS24_NDB/Cellist","https://shoeing1.github.io/MALIS24_NDB/Clown","https://shoeing1.github.io/MALIS24_NDB/Dokumentar","https://shoeing1.github.io/MALIS24_NDB/Ethnologe","https://shoeing1.github.io/MALIS24_NDB/Fotograf","https://shoeing1.github.io/MALIS24_NDB/Gastarbeiter","https://shoeing1.github.io/MALIS24_NDB/Geiger","https://shoeing1.github.io/MALIS24_NDB/Historiker","https://shoeing1.github.io/MALIS24_NDB/Innenarchitekt","https://shoeing1.github.io/MALIS24_NDB/Instrumentenbauer","https://shoeing1.github.io/MALIS24_NDB/Juwelier"],"2":["https://shoeing1.github.io/MALIS24_NDB/Bergarbeiter","https://shoeing1.github.io/MALIS24_NDB/Bibliothekar"],"3":["https://shoeing1.github.io/MALIS24_NDB/Altphilologe","https://shoeing1.github.io/MALIS24_NDB/Anatom","https://shoeing1.github.io/MALIS24_NDB/Arbeiter","https://shoeing1.github.io/MALIS24_NDB/Architekt","https://shoeing1.github.io/MALIS24_NDB/Archivar","https://shoeing1.github.io/MALIS24_NDB/Astrologe","https://shoeing1.github.io/MALIS24_NDB/Astronom","https://shoeing1.github.io/MALIS24_NDB/Autor","https://shoeing1.github.io/MALIS24_NDB/Außenminister","https://shoeing1.github.io/MALIS24_NDB/Bakteriologe","https://shoeing1.github.io/MALIS24_NDB/Bergarbeiter","https://shoeing1.github.io/MALIS24_NDB/Bibliothekar","https://shoeing1.github.io/MALIS24_NDB/Botschafter","https://shoeing1.github.io/MALIS24_NDB/Cellist","https://shoeing1.github.io/MALIS24_NDB/Clown","https://shoeing1.github.io/MALIS24_NDB/Dokumentar","https://shoeing1.github.io/MALIS24_NDB/Ethnologe","https://shoeing1.github.io/MALIS24_NDB/Fotograf","https://shoeing1.github.io/MALIS24_NDB/Gastarbeiter","https://shoeing1.github.io/MALIS24_NDB/Geiger","https://shoeing1.github.io/MALIS24_NDB/Historiker","https://shoeing1.github.io/MALIS24_NDB/Innenarchitekt","https://shoeing1.github.io/MALIS24_NDB/Instrumentenbauer","https://shoeing1.github.io/MALIS24_NDB/Juwelier"],"4":["https://shoeing1.github.io/MALIS24_NDB/Altphilologe","https://shoeing1.github.io/MALIS24_NDB/Anatom","https://shoeing1.github.io/MALIS24_NDB/Archivar","https://shoeing1.github.io/MALIS24_NDB/Autor","https://shoeing1.github.io/MALIS24_NDB/Cellist"],"5":["https://shoeing1.github.io/MALIS24_NDB/Altphilologe","https://shoeing1.github.io/MALIS24_NDB/Anatom","https://shoeing1.github.io/MALIS24_NDB/Arbeiter","https://shoeing1.github.io/MALIS24_NDB/Architekt","https://shoeing1.github.io/MALIS24_NDB/Archivar","https://shoeing1.github.io/MALIS24_NDB/Astrologe","https://shoeing1.github.io/MALIS24_NDB/Astronom","https://shoeing1.github.io/MALIS24_NDB/Autor","https://shoeing1.github.io/MALIS24_NDB/Außenminister","https://shoeing1.github.io/MALIS24_NDB/Bakteriologe","https://shoeing1.github.io/MALIS24_NDB/Bergarbeiter","https://shoeing1.github.io/MALIS24_NDB/Bibliothekar","https://shoeing1.github.io/MALIS24_NDB/Botschafter","https://shoeing1.github.io/MALIS24_NDB/Cellist","https://shoeing1.github.io/MALIS24_NDB/Clown","https://shoeing1.github.io/MALIS24_NDB/Dokumentar","https://shoeing1.github.io/MALIS24_NDB/Ethnologe","https://shoeing1.github.io/MALIS24_NDB/Fotograf","https://shoeing1.github.io/MALIS24_NDB/Gastarbeiter","https://shoeing1.github.io/MALIS24_NDB/Geiger","https://shoeing1.github.io/MALIS24_NDB/Historiker","https://shoeing1.github.io/MALIS24_NDB/Innenarchitekt","https://shoeing1.github.io/MALIS24_NDB/Instrumentenbauer","https://shoeing1.github.io/MALIS24_NDB/Juwelier"],"6":["https://shoeing1.github.io/MALIS24_NDB/Bakteriologe","https://shoeing1.github.io/MALIS24_NDB/Dokumentar","https://shoeing1.github.io/MALIS24_NDB/Fotograf","https://shoeing1.github.io/MALIS24_NDB/Gastarbeiter","https://shoeing1.github.io/MALIS24_NDB/Geiger","https://shoeing1.github.io/MALIS24_NDB/Historiker","https://shoeing1.github.io/MALIS24_NDB/Innenarchitekt","https://shoeing1.github.io/MALIS24_NDB/Instrumentenbauer","https://shoeing1.github.io/MALIS24_NDB/Juwelier"],"7":["https://shoeing1.github.io/MALIS24_NDB/Bibliothekar","https://shoeing1.github.io/MALIS24_NDB/Ethnologe","https://shoeing1.github.io/MALIS24_NDB/Instrumentenbauer","https://shoeing1.github.io/MALIS24_NDB/Juwelier"],"8":["https://shoeing1.github.io/MALIS24_NDB/Astrologe","https://shoeing1.github.io/MALIS24_NDB/Juwelier"],"9":["https://shoeing1.github.io/MALIS24_NDB/Altphilologe","https://shoeing1.github.io/MALIS24_NDB/Anatom","https://shoeing1.github.io/MALIS24_NDB/Fotograf","https://shoeing1.github.io/MALIS24_NDB/Gastarbeiter"],"10":["https://shoeing1.github.io/MALIS24_NDB/Astronom"],"11":["https://shoeing1.github.io/MALIS24_NDB/Geiger"],"13":["https://shoeing1.github.io/MALIS24_NDB/Altphilologe","https://shoeing1.github.io/MALIS24_NDB/Anatom","https://shoeing1.github.io/MALIS24_NDB/Arbeiter","https://shoeing1.github.io/MALIS24_NDB/Architekt","https://shoeing1.github.io/MALIS24_NDB/Archivar","https://shoeing1.github.io/MALIS24_NDB/Astrologe","https://shoeing1.github.io/MALIS24_NDB/Astronom","https://shoeing1.github.io/MALIS24_NDB/Autor","https://shoeing1.github.io/MALIS24_NDB/Außenminister","https://shoeing1.github.io/MALIS24_NDB/Bakteriologe","https://shoeing1.github.io/MALIS24_NDB/Bergarbeiter","https://shoeing1.github.io/MALIS24_NDB/Bibliothekar","https://shoeing1.github.io/MALIS24_NDB/Botschafter","https://shoeing1.github.io/MALIS24_NDB/Cellist","https://shoeing1.github.io/MALIS24_NDB/Clown","https://shoeing1.github.io/MALIS24_NDB/Dokumentar","https://shoeing1.github.io/MALIS24_NDB/Ethnologe","https://shoeing1.github.io/MALIS24_NDB/Fotograf","https://shoeing1.github.io/MALIS24_NDB/Gastarbeiter","https://shoeing1.github.io/MALIS24_NDB/Geiger","https://shoeing1.github.io/MALIS24_NDB/Historiker","https://shoeing1.github.io/MALIS24_NDB/Innenarchitekt","https://shoeing1.github.io/MALIS24_NDB/Instrumentenbauer","https://shoeing1.github.io/MALIS24_NDB/Juwelier"],"14":["https://shoeing1.github.io/MALIS24_NDB/Autor"],"16":["https://shoeing1.github.io/MALIS24_NDB/Bakteriologe"],"21":["https://shoeing1.github.io/MALIS24_NDB/Bergarbeiter"],"27":["https://shoeing1.github.io/MALIS24_NDB/Bibliothekar"],"35":["https://shoeing1.github.io/MALIS24_NDB/Altphilologe","https://shoeing1.github.io/MALIS24_NDB/Anatom","https://shoeing1.github.io/MALIS24_NDB/Arbeiter","https://shoeing1.github.io/MALIS24_NDB/Architekt","https://shoeing1.github.io/MALIS24_NDB/Archivar","https://shoeing1.github.io/MALIS24_NDB/Astrologe","https://shoeing1.github.io/MALIS24_NDB/Astronom","https://shoeing1.github.io/MALIS24_NDB/Autor","https://shoeing1.github.io/MALIS24_NDB/Außenminister","https://shoeing1.github.io/MALIS24_NDB/Bakteriologe","https://shoeing1.github.io/MALIS24_NDB/Bergarbeiter","https://shoeing1.github.io/MALIS24_NDB/Bibliothekar","https://shoeing1.github.io/MALIS24_NDB/Botschafter","https://shoeing1.github.io/MALIS24_NDB/Cellist","https://shoeing1.github.io/MALIS24_NDB/Clown","https://shoeing1.github.io/MALIS24_NDB/Dokumentar","https://shoeing1.github.io/MALIS24_NDB/Ethnologe","https://shoeing1.github.io/MALIS24_NDB/Fotograf","https://shoeing1.github.io/MALIS24_NDB/Gastarbeiter","https://shoeing1.github.io/MALIS24_NDB/Geiger","https://shoeing1.github.io/MALIS24_NDB/Historiker","https://shoeing1.github.io/MALIS24_NDB/Innenarchitekt","https://shoeing1.github.io/MALIS24_NDB/Instrumentenbauer","https://shoeing1.github.io/MALIS24_NDB/Juwelier"],"44":["https://shoeing1.github.io/MALIS24_NDB/Cellist"],"49":["https://shoeing1.github.io/MALIS24_NDB/Altphilologe","https://shoeing1.github.io/MALIS24_NDB/Anatom"],"50":["https://shoeing1.github.io/MALIS24_NDB/Arbeiter","https://shoeing1.github.io/MALIS24_NDB/Architekt","https://shoeing1.github.io/MALIS24_NDB/Archivar","https://shoeing1.github.io/MALIS24_NDB/Astrologe","https://shoeing1.github.io/MALIS24_NDB/Clown","https://shoeing1.github.io/MALIS24_NDB/Historiker"],"51":["https://shoeing1.github.io/MALIS24_NDB/Astronom","https://shoeing1.github.io/MALIS24_NDB/Autor","https://shoeing1.github.io/MALIS24_NDB/Außenminister","https://shoeing1.github.io/MALIS24_NDB/Bakteriologe"],"52":["https://shoeing1.github.io/MALIS24_NDB/Bergarbeiter","https://shoeing1.github.io/MALIS24_NDB/Bibliothekar"],"53":["https://shoeing1.github.io/MALIS24_NDB/Botschafter"],"54":["https://shoeing1.github.io/MALIS24_NDB/Altphilologe","https://shoeing1.github.io/MALIS24_NDB/Anatom","https://shoeing1.github.io/MALIS24_NDB/Cellist"],"55":["https://shoeing1.github.io/MALIS24_NDB/Arbeiter","https://shoeing1.github.io/MALIS24_NDB/Architekt","https://shoeing1.github.io/MALIS24_NDB/Archivar","https://shoeing1.github.io/MALIS24_NDB/Astrologe","https://shoeing1.github.io/MALIS24_NDB/Astronom","https://shoeing1.github.io/MALIS24_NDB/Autor","https://shoeing1.github.io/MALIS24_NDB/Außenminister","https://shoeing1.github.io/MALIS24_NDB/Bakteriologe","https://shoeing1.github.io/MALIS24_NDB/Bergarbeiter","https://shoeing1.github.io/MALIS24_NDB/Bibliothekar","https://shoeing1.github.io/MALIS24_NDB/Botschafter","https://shoeing1.github.io/MALIS24_NDB/Cellist","https://shoeing1.github.io/MALIS24_NDB/Clown","https://shoeing1.github.io/MALIS24_NDB/Dokumentar","https://shoeing1.github.io/MALIS24_NDB/Ethnologe","https://shoeing1.github.io/MALIS24_NDB/Fotograf"],"56":["https://shoeing1.github.io/MALIS24_NDB/Dokumentar","https://shoeing1.github.io/MALIS24_NDB/Gastarbeiter","https://shoeing1.github.io/MALIS24_NDB/Geiger","https://shoeing1.github.io/MALIS24_NDB/Historiker","https://shoeing1.github.io/MALIS24_NDB/Innenarchitekt","https://shoeing1.github.io/MALIS24_NDB/Instrumentenbauer","https://shoeing1.github.io/MALIS24_NDB/Juwelier"],"57":["https://shoeing1.github.io/MALIS24_NDB/Ethnologe"],"59":["https://shoeing1.github.io/MALIS24_NDB/Fotograf"],"60":["https://shoeing1.github.io/MALIS24_NDB/Gastarbeiter"],"61":["https://shoeing1.github.io/MALIS24_NDB/Dokumentar","https://shoeing1.github.io/MALIS24_NDB/Geiger"],"65":["https://shoeing1.github.io/MALIS24_NDB/Historiker"],"66":["https://shoeing1.github.io/MALIS24_NDB/Innenarchitekt","https://shoeing1.github.io/MALIS24_NDB/Instrumentenbauer"],"67":["https://shoeing1.github.io/MALIS24_NDB/Instrumentenbauer","https://shoeing1.github.io/MALIS24_NDB/Juwelier"],"77":["https://shoeing1.github.io/MALIS24_NDB/Ethnologe"],"78":["https://shoeing1.github.io/MALIS24_NDB/Juwelier"],"90":["https://shoeing1.github.io/MALIS24_NDB/Altphilologe"],"94":["https://shoeing1.github.io/MALIS24_NDB/Anatom"],"96":["https://shoeing1.github.io/MALIS24_NDB/Fotograf"],"135":["https://shoeing1.github.io/MALIS24_NDB/Altphilologe","https://shoeing1.github.io/MALIS24_NDB/Anatom","https://shoeing1.github.io/MALIS24_NDB/Arbeiter","https://shoeing1.github.io/MALIS24_NDB/Architekt","https://shoeing1.github.io/MALIS24_NDB/Archivar","https://shoeing1.github.io/MALIS24_NDB/Astrologe","https://shoeing1.github.io/MALIS24_NDB/Astronom","https://shoeing1.github.io/MALIS24_NDB/Autor","https://shoeing1.github.io/MALIS24_NDB/Außenminister","https://shoeing1.github.io/MALIS24_NDB/Bakteriologe","https://shoeing1.github.io/MALIS24_NDB/Bergarbeiter","https://shoeing1.github.io/MALIS24_NDB/Bibliothekar","https://shoeing1.github.io/MALIS24_NDB/Botschafter","https://shoeing1.github.io/MALIS24_NDB/Cellist","https://shoeing1.github.io/MALIS24_NDB/Clown","https://shoeing1.github.io/MALIS24_NDB/Dokumentar","https://shoeing1.github.io/MALIS24_NDB/Ethnologe","https://shoeing1.github.io/MALIS24_NDB/Fotograf","https://shoeing1.github.io/MALIS24_NDB/Gastarbeiter","https://shoeing1.github.io/MALIS24_NDB/Geiger","https://shoeing1.github.io/MALIS24_NDB/Historiker","https://shoeing1.github.io/MALIS24_NDB/Innenarchitekt","https://shoeing1.github.io/MALIS24_NDB/Instrumentenbauer","https://shoeing1.github.io/MALIS24_NDB/Juwelier"],"354":["https://shoeing1.github.io/MALIS24_NDB/Altphilologe","https://shoeing1.github.io/MALIS24_NDB/Anatom"],"355":["https://shoeing1.github.io/MALIS24_NDB/Arbeiter","https://shoeing1.github.io/MALIS24_NDB/Architekt","https://shoeing1.github.io/MALIS24_NDB/Archivar","https://shoeing1.github.io/MALIS24_NDB/Astrologe","https://shoeing1.github.io/MALIS24_NDB/Astronom","https://shoeing1.github.io/MALIS24_NDB/Autor","https://shoeing1.github.io/MALIS24_NDB/Außenminister","https://shoeing1.github.io/MALIS24_NDB/Bakteriologe","https://shoeing1.github.io/MALIS24_NDB/Bergarbeiter","https://shoeing1.github.io/MALIS24_NDB/Bibliothekar","https://shoeing1.github.io/MALIS24_NDB/Botschafter","https://shoeing1.github.io/MALIS24_NDB/Cellist","https://shoeing1.github.io/MALIS24_NDB/Clown","https://shoeing1.github.io/MALIS24_NDB/Dokumentar","https://shoeing1.github.io/MALIS24_NDB/Ethnologe","https://shoeing1.github.io/MALIS24_NDB/Fotograf"],"356":["https://shoeing1.github.io/MALIS24_NDB/Gastarbeiter","https://shoeing1.github.io/MALIS24_NDB/Geiger","https://shoeing1.github.io/MALIS24_NDB/Historiker","https://shoeing1.github.io/MALIS24_NDB/Innenarchitekt","https://shoeing1.github.io/MALIS24_NDB/Instrumentenbauer","https://shoeing1.github.io/MALIS24_NDB/Juwelier"],"490":["https://shoeing1.github.io/MALIS24_NDB/Altphilologe"],"494":["https://shoeing1.github.io/MALIS24_NDB/Anatom"],"500":["https://shoeing1.github.io/MALIS24_NDB/Arbeiter"],"503":["https://shoeing1.github.io/MALIS24_NDB/Architekt"],"504":["https://shoeing1.github.io/MALIS24_NDB/Archivar"],"508":["https://shoeing1.github.io/MALIS24_NDB/Astrologe"],"510":["https://shoeing1.github.io/MALIS24_NDB/Astronom"],"513":["https://shoeing1.github.io/MALIS24_NDB/Außenminister"],"514":["https://shoeing1.github.io/MALIS24_NDB/Autor"],"516":["https://shoeing1.github.io/MALIS24_NDB/Bakteriologe"],"521":["https://shoeing1.github.io/MALIS24_NDB/Bergarbeiter"],"527":["https://shoeing1.github.io/MALIS24_NDB/Bibliothekar"],"535":["https://shoeing1.github.io/MALIS24_NDB/Botschafter"],"544":["https://shoeing1.github.io/MALIS24_NDB/Cellist"],"549":["https://shoeing1.github.io/MALIS24_NDB/Altphilologe","https://shoeing1.github.io/MALIS24_NDB/Anatom"],"550":["https://shoeing1.github.io/MALIS24_NDB/Arbeiter","https://shoeing1.github.io/MALIS24_NDB/Architekt","https://shoeing1.github.io/MALIS24_NDB/Archivar","https://shoeing1.github.io/MALIS24_NDB/Astrologe","https://shoeing1.github.io/MALIS24_NDB/Clown"],"551":["https://shoeing1.github.io/MALIS24_NDB/Astronom","https://shoeing1.github.io/MALIS24_NDB/Autor","https://shoeing1.github.io/MALIS24_NDB/Außenminister","https://shoeing1.github.io/MALIS24_NDB/Bakteriologe"],"552":["https://shoeing1.github.io/MALIS24_NDB/Bergarbeiter","https://shoeing1.github.io/MALIS24_NDB/Bibliothekar"],"553":["https://shoeing1.github.io/MALIS24_NDB/Botschafter"],"554":["https://shoeing1.github.io/MALIS24_NDB/Cellist"],"555":["https://shoeing1.github.io/MALIS24_NDB/Clown"],"556":["https://shoeing1.github.io/MALIS24_NDB/Dokumentar"],"557":["https://shoeing1.github.io/MALIS24_NDB/Ethnologe"],"559":["https://shoeing1.github.io/MALIS24_NDB/Fotograf"],"560":["https://shoeing1.github.io/MALIS24_NDB/Gastarbeiter"],"561":["https://shoeing1.github.io/MALIS24_NDB/Dokumentar","https://shoeing1.github.io/MALIS24_NDB/Geiger"],"565":["https://shoeing1.github.io/MALIS24_NDB/Historiker"],"566":["https://shoeing1.github.io/MALIS24_NDB/Innenarchitekt","https://shoeing1.github.io/MALIS24_NDB/Instrumentenbauer"],"567":["https://shoeing1.github.io/MALIS24_NDB/Juwelier"],"577":["https://shoeing1.github.io/MALIS24_NDB/Ethnologe"],"596":["https://shoeing1.github.io/MALIS24_NDB/Fotograf"],"609":["https://shoeing1.github.io/MALIS24_NDB/Gastarbeiter"],"611":["https://shoeing1.github.io/MALIS24_NDB/Geiger"],"650":["https://shoeing1.github.io/MALIS24_NDB/Historiker"],"666":["https://shoeing1.github.io/MALIS24_NDB/Innenarchitekt"],"667":["https://shoeing1.github.io/MALIS24_NDB/Instrumentenbauer"],"678":["https://shoeing1.github.io/MALIS24_NDB/Juwelier"],"1354":["https://shoeing1.github.io/MALIS24_NDB/Altphilologe","https://shoeing1.github.io/MALIS24_NDB/Anatom"],"1355":["https://shoeing1.github.io/MALIS24_NDB/Arbeiter","https://shoeing1.github.io/MALIS24_NDB/Architekt","https://shoeing1.github.io/MALIS24_NDB/Archivar","https://shoeing1.github.io/MALIS24_NDB/Astrologe","https://shoeing1.github.io/MALIS24_NDB/Astronom","https://shoeing1.github.io/MALIS24_NDB/Autor","https://shoeing1.github.io/MALIS24_NDB/Außenminister","https://shoeing1.github.io/MALIS24_NDB/Bakteriologe","https://shoeing1.github.io/MALIS24_NDB/Bergarbeiter","https://shoeing1.github.io/MALIS24_NDB/Bibliothekar","https://shoeing1.github.io/MALIS24_NDB/Botschafter","https://shoeing1.github.io/MALIS24_NDB/Cellist","https://shoeing1.github.io/MALIS24_NDB/Clown","https://shoeing1.github.io/MALIS24_NDB/Dokumentar","https://shoeing1.github.io/MALIS24_NDB/Ethnologe","https://shoeing1.github.io/MALIS24_NDB/Fotograf"],"1356":["https://shoeing1.github.io/MALIS24_NDB/Gastarbeiter","https://shoeing1.github.io/MALIS24_NDB/Geiger","https://shoeing1.github.io/MALIS24_NDB/Historiker","https://shoeing1.github.io/MALIS24_NDB/Innenarchitekt","https://shoeing1.github.io/MALIS24_NDB/Instrumentenbauer","https://shoeing1.github.io/MALIS24_NDB/Juwelier"],"3549":["https://shoeing1.github.io/MALIS24_NDB/Altphilologe","https://shoeing1.github.io/MALIS24_NDB/Anatom"],"3550":["https://shoeing1.github.io/MALIS24_NDB/Arbeiter","https://shoeing1.github.io/MALIS24_NDB/Architekt","https://shoeing1.github.io/MALIS24_NDB/Archivar","https://shoeing1.github.io/MALIS24_NDB/Astrologe"],"3551":["https://shoeing1.github.io/MALIS24_NDB/Astronom","https://shoeing1.github.io/MALIS24_NDB/Autor","https://shoeing1.github.io/MALIS24_NDB/Außenminister","https://shoeing1.github.io/MALIS24_NDB/Bakteriologe"],"3552":["https://shoeing1.github.io/MALIS24_NDB/Bergarbeiter","https://shoeing1.github.io/MALIS24_NDB/Bibliothekar"],"3553":["https://shoeing1.github.io/MALIS24_NDB/Botschafter"],"3554":["https://shoeing1.github.io/MALIS24_NDB/Cellist"],"3555":["https://shoeing1.github.io/MALIS24_NDB/Clown"],"3556":["https://shoeing1.github.io/MALIS24_NDB/Dokumentar"],"3557":["https://shoeing1.github.io/MALIS24_NDB/Ethnologe"],"3559":["https://shoeing1.github.io/MALIS24_NDB/Fotograf"],"3560":["https://shoeing1.github.io/MALIS24_NDB/Gastarbeiter"],"3561":["https://shoeing1.github.io/MALIS24_NDB/Geiger"],"3565":["https://shoeing1.github.io/MALIS24_NDB/Historiker"],"3566":["https://shoeing1.github.io/MALIS24_NDB/Innenarchitekt","https://shoeing1.github.io/MALIS24_NDB/Instrumentenbauer"],"3567":["https://shoeing1.github.io/MALIS24_NDB/Juwelier"],"5490":["https://shoeing1.github.io/MALIS24_NDB/Altphilologe"],"5494":["https://shoeing1.github.io/MALIS24_NDB/Anatom"],"5500":["https://shoeing1.github.io/MALIS24_NDB/Arbeiter"],"5503":["https://shoeing1.github.io/MALIS24_NDB/Architekt"],"5504":["https://shoeing1.github.io/MALIS24_NDB/Archivar"],"5508":["https://shoeing1.github.io/MALIS24_NDB/Astrologe"],"5510":["https://shoeing1.github.io/MALIS24_NDB/Astronom"],"5513":["https://shoeing1.github.io/MALIS24_NDB/Außenminister"],"5514":["https://shoeing1.github.io/MALIS24_NDB/Autor"],"5516":["https://shoeing1.github.io/MALIS24_NDB/Bakteriologe"],"5521":["https://shoeing1.github.io/MALIS24_NDB/Bergarbeiter"],"5527":["https://shoeing1.github.io/MALIS24_NDB/Bibliothekar"],"5535":["https://shoeing1.github.io/MALIS24_NDB/Botschafter"],"5544":["https://shoeing1.github.io/MALIS24_NDB/Cellist"],"5550":["https://shoeing1.github.io/MALIS24_NDB/Clown"],"5561":["https://shoeing1.github.io/MALIS24_NDB/Dokumentar"],"5577":["https://shoeing1.github.io/MALIS24_NDB/Ethnologe"],"5596":["https://shoeing1.github.io/MALIS24_NDB/Fotograf"],"5609":["https://shoeing1.github.io/MALIS24_NDB/Gastarbeiter"],"5611":["https://shoeing1.github.io/MALIS24_NDB/Geiger"],"5650":["https://shoeing1.github.io/MALIS24_NDB/Historiker"],"5666":["https://shoeing1.github.io/MALIS24_NDB/Innenarchitekt"],"5667":["https://shoeing1.github.io/MALIS24_NDB/Instrumentenbauer"],"5678":["https://shoeing1.github.io/MALIS24_NDB/Juwelier"],"13549":["https://shoeing1.github.io/MALIS24_NDB/Altphilologe","https://shoeing1.github.io/MALIS24_NDB/Anatom"],"13550":["https://shoeing1.github.io/MALIS24_NDB/Arbeiter","https://shoeing1.github.io/MALIS24_NDB/Architekt","https://shoeing1.github.io/MALIS24_NDB/Archivar","https://shoeing1.github.io/MALIS24_NDB/Astrologe"],"13551":["https://shoeing1.github.io/MALIS24_NDB/Astronom","https://shoeing1.github.io/MALIS24_NDB/Autor","https://shoeing1.github.io/MALIS24_NDB/Außenminister","https://shoeing1.github.io/MALIS24_NDB/Bakteriologe"],"13552":["https://shoeing1.github.io/MALIS24_NDB/Bergarbeiter","https://shoeing1.github.io/MALIS24_NDB/Bibliothekar"],"13553":["https://shoeing1.github.io/MALIS24_NDB/Botschafter"],"13554":["https://shoeing1.github.io/MALIS24_NDB/Cellist"],"13555":["https://shoeing1.github.io/MALIS24_NDB/Clown"],"13556":["https://shoeing1.github.io/MALIS24_NDB/Dokumentar"],"13557":["https://shoeing1.github.io/MALIS24_NDB/Ethnologe"],"13559":["https://shoeing1.github.io/MALIS24_NDB/Fotograf"],"13560":["https://shoeing1.github.io/MALIS24_NDB/Gastarbeiter"],"13561":["https://shoeing1.github.io/MALIS24_NDB/Geiger"],"13565":["https://shoeing1.github.io/MALIS24_NDB/Historiker"],"13566":["https://shoeing1.github.io/MALIS24_NDB/Innenarchitekt","https://shoeing1.github.io/MALIS24_NDB/Instrumentenbauer"],"13567":["https://shoeing1.github.io/MALIS24_NDB/Juwelier"],"35490":["https://shoeing1.github.io/MALIS24_NDB/Altphilologe"],"35494":["https://shoeing1.github.io/MALIS24_NDB/Anatom"],"35500":["https://shoeing1.github.io/MALIS24_NDB/Arbeiter"],"35503":["https://shoeing1.github.io/MALIS24_NDB/Architekt"],"35504":["https://shoeing1.github.io/MALIS24_NDB/Archivar"],"35508":["https://shoeing1.github.io/MALIS24_NDB/Astrologe"],"35510":["https://shoeing1.github.io/MALIS24_NDB/Astronom"],"35513":["https://shoeing1.github.io/MALIS24_NDB/Außenminister"],"35514":["https://shoeing1.github.io/MALIS24_NDB/Autor"],"35516":["https://shoeing1.github.io/MALIS24_NDB/Bakteriologe"],"35521":["https://shoeing1.github.io/MALIS24_NDB/Bergarbeiter"],"35527":["https://shoeing1.github.io/MALIS24_NDB/Bibliothekar"],"35535":["https://shoeing1.github.io/MALIS24_NDB/Botschafter"],"35544":["https://shoeing1.github.io/MALIS24_NDB/Cellist"],"35550":["https://shoeing1.github.io/MALIS24_NDB/Clown"],"35561":["https://shoeing1.github.io/MALIS24_NDB/Dokumentar"],"35577":["https://shoeing1.github.io/MALIS24_NDB/Ethnologe"],"35596":["https://shoeing1.github.io/MALIS24_NDB/Fotograf"],"35609":["https://shoeing1.github.io/MALIS24_NDB/Gastarbeiter"],"35611":["https://shoeing1.github.io/MALIS24_NDB/Geiger"],"35650":["https://shoeing1.github.io/MALIS24_NDB/Historiker"],"35666":["https://shoeing1.github.io/MALIS24_NDB/Innenarchitekt"],"35667":["https://shoeing1.github.io/MALIS24_NDB/Instrumentenbauer"],"35678":["https://shoeing1.github.io/MALIS24_NDB/Juwelier"],"135490":["https://shoeing1.github.io/MALIS24_NDB/Altphilologe"],"135494":["https://shoeing1.github.io/MALIS24_NDB/Anatom"],"135500":["https://shoeing1.github.io/MALIS24_NDB/Arbeiter"],"135503":["https://shoeing1.github.io/MALIS24_NDB/Architekt"],"135504":["https://shoeing1.github.io/MALIS24_NDB/Archivar"],"135508":["https://shoeing1.github.io/MALIS24_NDB/Astrologe"],"135510":["https://shoeing1.github.io/MALIS24_NDB/Astronom"],"135513":["https://shoeing1.github.io/MALIS24_NDB/Außenminister"],"135514":["https://shoeing1.github.io/MALIS24_NDB/Autor"],"135516":["https://shoeing1.github.io/MALIS24_NDB/Bakteriologe"],"135521":["https://shoeing1.github.io/MALIS24_NDB/Bergarbeiter"],"135527":["https://shoeing1.github.io/MALIS24_NDB/Bibliothekar"],"135535":["https://shoeing1.github.io/MALIS24_NDB/Botschafter"],"135544":["https://shoeing1.github.io/MALIS24_NDB/Cellist"],"135550":["https://shoeing1.github.io/MALIS24_NDB/Clown"],"135561":["https://shoeing1.github.io/MALIS24_NDB/Dokumentar"],"135577":["https://shoeing1.github.io/MALIS24_NDB/Ethnologe"],"135596":["https://shoeing1.github.io/MALIS24_NDB/Fotograf"],"135609":["https://shoeing1.github.io/MALIS24_NDB/Gastarbeiter"],"135611":["https://shoeing1.github.io/MALIS24_NDB/Geiger"],"135650":["https://shoeing1.github.io/MALIS24_NDB/Historiker"],"135666":["https://shoeing1.github.io/MALIS24_NDB/Innenarchitekt"],"135667":["https://shoeing1.github.io/MALIS24_NDB/Instrumentenbauer"],"135678":["https://shoeing1.github.io/MALIS24_NDB/Juwelier"],"00":["https://shoeing1.github.io/MALIS24_NDB/Arbeiter"],"03":["https://shoeing1.github.io/MALIS24_NDB/Architekt"],"04":["https://shoeing1.github.io/MALIS24_NDB/Archivar"],"08":["https://shoeing1.github.io/MALIS24_NDB/Astrologe"],"09":["https://shoeing1.github.io/MALIS24_NDB/Gastarbeiter"]},{},{},{},{},{},{},{},{}]